pyforce/__init__.py
pyforce/commands.py
pyforce/exceptions.py
pyforce/models.py
pyforce/py.typed
pyforce/utils.py
pyforce_p4-0.1.1.dist-info/METADATA
pyforce_p4-0.1.1.dist-info/WHEEL
pyforce_p4-0.1.1.dist-info/licenses/LICENSE
pyforce_p4-0.1.1.dist-info/RECORD
