Metadata-Version: 2.3
Name: pyforce-p4
Version: 0.1.1
Summary: Python wrapper for Perforce p4 command-line client
Project-URL: Github, https://github.com/tahv/pyforce
Project-URL: Changelog, https://github.com/tahv/pyforce/blob/main/CHANGELOG.md
Project-URL: Documentation, https://pyforce.readthedocs.io/en/latest
Author: Thibaud Gambier
License-Expression: MIT
License-File: LICENSE
Classifier: Development Status :: 4 - Beta
Classifier: License :: OSI Approved :: MIT License
Classifier: Programming Language :: Python :: 3.7
Classifier: Programming Language :: Python :: 3.8
Classifier: Programming Language :: Python :: 3.9
Classifier: Programming Language :: Python :: 3.10
Classifier: Programming Language :: Python :: 3.11
Classifier: Programming Language :: Python :: 3.12
Classifier: Programming Language :: Python :: Implementation :: CPython
Classifier: Typing :: Typed
Requires-Python: >=3.7
Requires-Dist: pydantic
Requires-Dist: typing-extensions
Provides-Extra: dev
Requires-Dist: pyforce-p4[docs,mypy,style,tests]; extra == 'dev'
Provides-Extra: docs
Requires-Dist: autodoc-pydantic; extra == 'docs'
Requires-Dist: enum-tools[sphinx]; extra == 'docs'
Requires-Dist: furo; extra == 'docs'
Requires-Dist: myst-parser; extra == 'docs'
Requires-Dist: sphinx; extra == 'docs'
Requires-Dist: sphinx-autobuild; extra == 'docs'
Provides-Extra: mypy
Requires-Dist: mypy; extra == 'mypy'
Requires-Dist: pytest; extra == 'mypy'
Provides-Extra: style
Requires-Dist: ruff; extra == 'style'
Provides-Extra: tests
Requires-Dist: coverage; extra == 'tests'
Requires-Dist: pytest; extra == 'tests'
